vault_search_replace/__init__.py
vault_search_replace/vault_search_replace.py
vault_search_replace-0.1.2.dist-info/METADATA
vault_search_replace-0.1.2.dist-info/WHEEL
vault_search_replace-0.1.2.dist-info/entry_points.txt
vault_search_replace-0.1.2.dist-info/licenses/LICENSE
vault_search_replace-0.1.2.dist-info/RECORD
