Metadata-Version: 2.4
Name: vault-search-replace
Version: 0.1.2
Summary: A simple search and replace command line utility for Hashicorp Vault
License-File: LICENSE
Requires-Python: >=3.13
Requires-Dist: click>=8.1.7
Requires-Dist: hvac>=2.3.0
Requires-Dist: loguru>=0.7.2
Requires-Dist: python-dotenv>=1.0.1
Requires-Dist: ruff>=0.6.9
Requires-Dist: typer>=0.12.5
